plurk/__init__.py
plurk/exceptions.py
plurk/utils.py
plurk/apis/__init__.py
plurk/apis/alerts.py
plurk/apis/base.py
plurk/apis/blocks.py
plurk/apis/cliques.py
plurk/apis/emoticons.py
plurk/apis/friends_fans.py
plurk/apis/helper.py
plurk/apis/plurk_search.py
plurk/apis/profile.py
plurk/apis/realtime.py
plurk/apis/responses.py
plurk/apis/timeline.py
plurk/apis/user_search.py
plurk/apis/users.py
plurk/async_apis/__init__.py
plurk/async_apis/alerts.py
plurk/async_apis/base.py
plurk/async_apis/blocks.py
plurk/async_apis/cliques.py
plurk/async_apis/emoticons.py
plurk/async_apis/friends_fans.py
plurk/async_apis/helper.py
plurk/async_apis/plurk_search.py
plurk/async_apis/profile.py
plurk/async_apis/realtime.py
plurk/async_apis/responses.py
plurk/async_apis/timeline.py
plurk/async_apis/user_search.py
plurk/async_apis/users.py
plurk/clients/__init__.py
plurk/clients/async_client.py
plurk/clients/base.py
plurk/clients/client.py
plurk/enums/__init__.py
plurk/enums/abuse_category.py
plurk/enums/alert_type.py
plurk/enums/avatar_size.py
plurk/enums/channel_data_entry_type.py
plurk/enums/filter.py
plurk/enums/language.py
plurk/enums/privacy.py
plurk/enums/qualifier.py
plurk/enums/relationship.py
plurk/models/__init__.py
plurk/models/alert.py
plurk/models/base.py
plurk/models/blocks.py
plurk/models/general_resps.py
plurk/models/karma_stats.py
plurk/models/plurk.py
plurk/models/profile.py
plurk/models/response.py
plurk/models/search.py
plurk/models/timeline.py
plurk/models/user_channel.py
plurk/models/user_data.py
plurk_py-0.0.5.dist-info/LICENSE
plurk_py-0.0.5.dist-info/METADATA
plurk_py-0.0.5.dist-info/WHEEL
plurk_py-0.0.5.dist-info/top_level.txt
plurk_py-0.0.5.dist-info/RECORD
